sarers/__init__.py
sarers-0.1.dist-info/METADATA
sarers-0.1.dist-info/WHEEL
sarers-0.1.dist-info/license.txt
sarers-0.1.dist-info/top_level.txt
sarers-0.1.dist-info/RECORD
