Metadata-Version: 2.1
Name: sarers
Version: 0.1
Summary: nigeria
Author: nigeria
Author-email: niveco1990@bizatop.com
Classifier: Programming Language :: Python :: 3
Classifier: License :: OSI Approved :: MIT License
Classifier: Operating System :: OS Independent
License-File: license.txt
